{
    "title": "Nerd³ Plays... Fallout - Something Old",
    "date": "2016-11-12",
    "links": [],
    "music": [],
    "source": {
        "name": "OfficialNerdCubed",
        "url": "https://www.youtube.com/channel/UCKab3hYnOoTZZbEUQBMx-ww"
    },
    "websiteData": {
        "path": "/videos/nerdcubed-plays-fallout-something-old/",
        "small": "background: url(/img/h/61cc356495c34dd8a0dc89a81ac048fd.jpg) -448px -378px no-repeat; width: 224px; height: 126px",
        "tags": [
            "channel_1"
        ]
    }
}