{
    "title": "Nerd³ Plays... Wrestling Revolution 3D - Outta Nowhere",
    "date": "2017-07-30",
    "links": [],
    "music": [],
    "source": {
        "name": "OfficialNerdCubed",
        "url": "https://www.youtube.com/channel/UCKab3hYnOoTZZbEUQBMx-ww"
    },
    "websiteData": {
        "path": "/videos/nerdcubed-plays-wrestling-revolution-3d-outta-nowhere/",
        "small": "background: url(/img/h/1fff7e3d422186c26722137e939b86cb.jpg) 0px 0px no-repeat; width: 224px; height: 126px",
        "tages": [
            "channel_1"
        ]
    }
}