{
    "title": "Nerd³ Plays... WWE 2K17 - The Phenomenal One",
    "date": "2016-10-15",
    "links": [],
    "music": [],
    "source": {
        "name": "OfficialNerdCubed",
        "url": "https://www.youtube.com/channel/UCKab3hYnOoTZZbEUQBMx-ww"
    },
    "websiteData": {
        "path": "/videos/nerdcubed-plays-wwe-2k17-the-phenomenal-one/",
        "small": "background: url(/img/h/e270e1768e28be8ffe512288b8ca8536.jpg) -672px -252px no-repeat; width: 224px; height: 126px",
        "tags": [
            "channel_1"
        ]
    }
}