{
    "title": "Nerd³ Challenges! Do Esports! -- Counter-Strike: Global Offensive",
    "date": "2014-08-05",
    "links": [
        {
            "name": "Steam Link",
            "url": "http://store.steampowered.com/app/730/"
        }
    ],
    "music": [
        {
            "credit": "Dan Bull",
            "track": "End theme",
            "url": "http://www.youtube.com/user/douglby"
        }
    ],
    "source": {
        "name": "OfficialNerdCubed",
        "url": "https://www.youtube.com/channel/UCKab3hYnOoTZZbEUQBMx-ww"
    },
    "websiteData": {
        "path": "/videos/nerdcubed-challenges-do-esports-counter-strike-global-offensive/",
        "small": "background: url(/img/h/ab2da44b4e1d840c2f65263ca9837b33.jpg) 0px -504px no-repeat; width: 224px; height: 126px",
        "tages": [
            "channel_1"
        ]
    }
}