{
    "title": "Dad³ Plays... Hardware: Rivals... Again!",
    "date": "2016-04-09",
    "links": [],
    "music": [],
    "source": {
        "name": "OfficialDadCubed",
        "url": "https://www.youtube.com/channel/UCjGOhTp9qmQHtlW5DKQ15jg"
    },
    "websiteData": {
        "path": "/videos/dadcubed-plays-hardware-rivals-again/",
        "small": "background: url(/img/h/b7a4e4969f61476147a25e4a7dae9e2b.jpg) 0px -504px no-repeat; width: 224px; height: 126px",
        "tags": [
            "channel_3"
        ]
    }
}