{
    "title": "Nerd³ Challenges! FPS Jet Attack! - GTA Online",
    "date": "2015-03-31",
    "links": [
        {
            "name": "Game Link",
            "url": "http://www.rockstargames.com/V/"
        }
    ],
    "music": [
        {
            "credit": "Dan Bull",
            "track": "End theme",
            "url": "http://www.youtube.com/user/douglby"
        }
    ],
    "source": {
        "name": "OfficialNerdCubed",
        "url": "https://www.youtube.com/channel/UCKab3hYnOoTZZbEUQBMx-ww"
    },
    "websiteData": {
        "path": "/videos/nerdcubed-challenges-fps-jet-attack-gta-online/",
        "small": "background: url(/img/h/a6462c02948383fb45426d556efda733.jpg) -224px -378px no-repeat; width: 224px; height: 126px",
        "tages": [
            "channel_1"
        ]
    }
}