{
    "title": "Little and Cubed - Mini Football - GTA Online",
    "date": "2014-05-11",
    "links": [
        {
            "name": "Play the map yourselves --",
            "url": "http://rsg.ms/1noLdtG"
        }
    ],
    "music": [],
    "source": {
        "name": "inthelittlewood",
        "url": "https://www.youtube.com/channel/UCWiPkogV65gqqNkwqci4yZA"
    },
    "websiteData": {
        "path": "/videos/little-and-cubed-mini-football-gta-online/",
        "small": "background: url(/img/h/f503119f926bddf6f3cd92a780f966ca.jpg) 0px -504px no-repeat; width: 224px; height: 126px",
        "tages": [
            "other_channel"
        ]
    }
}