{
    "title": "Little and Cubed: Catching Cars - GTA Online",
    "date": "2014-01-27",
    "links": [],
    "music": [],
    "source": {
        "name": "inthelittlewood",
        "url": "https://www.youtube.com/channel/UCWiPkogV65gqqNkwqci4yZA"
    },
    "websiteData": {
        "path": "/videos/little-and-cubed-catching-cars-gta-online/",
        "small": "background: url(/img/h/9796273602a83d81539b780063760462.jpg) -224px -378px no-repeat; width: 224px; height: 126px",
        "tages": [
            "other_channel"
        ]
    }
}