{
    "title": "Nerd³ Plays... The Great Language Game - Say Again?",
    "date": "2017-02-27",
    "links": [],
    "music": [],
    "source": {
        "name": "OfficialNerdCubed",
        "url": "https://www.youtube.com/channel/UCKab3hYnOoTZZbEUQBMx-ww"
    },
    "websiteData": {
        "path": "/videos/nerdcubed-plays-the-great-language-game-say-again/",
        "small": "background: url(/img/h/9120fca398a12f1ff90ec78c90be7409.jpg) -224px -252px no-repeat; width: 224px; height: 126px",
        "tages": [
            "channel_1"
        ]
    }
}