{
    "title": "Nerd³'s Lego Tuesdays - Lego Dimensions Haul",
    "date": "2016-12-23",
    "links": [],
    "music": [],
    "source": {
        "name": "Officiallynerdcubed",
        "url": "https://www.youtube.com/channel/UCwfFfKK8h1PBJkbv1tJjWJg"
    },
    "websiteData": {
        "path": "/videos/nerdcubed-lego-tuesdays-lego-dimensions-haul/",
        "small": "background: url(/img/h/fe0f31cfeab94fc650a80edfdc2ee799.jpg) 0px -504px no-repeat; width: 224px; height: 126px",
        "tages": [
            "channel_2"
        ]
    }
}