{
    "title": "Nerd³ Plays with Mods! Flan's Mod",
    "date": "2012-04-07",
    "links": [
        {
            "name": "Download the Mod here!",
            "url": "http://www.minecraftforum.net/topic/182918-124flans-mod-rewritten-and-now-totally-awesome/"
        }
    ],
    "music": [
        {
            "credit": "Kevin MacLeod",
            "track": "Danse Macabre - Low Strings Finale",
            "url": "http://www.incompetech.com/"
        },
        {
            "credit": "Kevin MacLeod",
            "track": "Rising",
            "url": "http://www.incompetech.com/"
        }
    ],
    "source": {
        "name": "OfficialNerdCubed",
        "url": "https://www.youtube.com/channel/UCKab3hYnOoTZZbEUQBMx-ww"
    },
    "websiteData": {
        "path": "/videos/nerdcubed-plays-with-mods-flan-s-mod/",
        "small": "background: url(/img/h/fcbc663550d3eb68c5050efbe2a84859.jpg) -224px 0px no-repeat; width: 224px; height: 126px",
        "tags": [
            "channel_1"
        ]
    }
}