{
    "title": "The Son-Days of Dad³ - Saints Row The Third - Part 5",
    "date": "2016-11-27",
    "links": [],
    "music": [],
    "source": {
        "name": "OfficialDadCubed",
        "url": "https://www.youtube.com/channel/UCjGOhTp9qmQHtlW5DKQ15jg"
    },
    "websiteData": {
        "path": "/videos/the-son-days-of-dadcubed-saints-row-the-third-part-5/",
        "small": "background: url(/img/h/d4bfefc6a260a760b48b14369ef62da1.jpg) -224px -252px no-repeat; width: 224px; height: 126px",
        "tages": [
            "channel_3"
        ]
    }
}