{
    "title": "Nerd³ Plays... Hot Dogs Horseshoes & Hand Grenades - Revolutions",
    "date": "2017-07-26",
    "links": [],
    "music": [],
    "source": {
        "name": "OfficialNerdCubed",
        "url": "https://www.youtube.com/channel/UCKab3hYnOoTZZbEUQBMx-ww"
    },
    "websiteData": {
        "path": "/videos/nerdcubed-plays-hot-dogs-horseshoes-hand-grenades-revolutions/",
        "small": "background: url(/img/h/b7643ffe4071f11f6c6d8a8f523ccc9f.jpg) -448px -504px no-repeat; width: 224px; height: 126px",
        "tags": [
            "channel_1"
        ]
    }
}